llm_atc/__init__.py
llm_atc/cli.py
llm_atc/config/serve/serve.yml
llm_atc/config/train/vicuna.yml
llm_atc/constants.py
llm_atc/launch.py
llm_atc/run.py
llm_atc/serve.py
llm_atc-0.1.7.dist-info/LICENSE
llm_atc-0.1.7.dist-info/METADATA
llm_atc-0.1.7.dist-info/WHEEL
llm_atc-0.1.7.dist-info/entry_points.txt
llm_atc-0.1.7.dist-info/RECORD
