Metadata-Version: 2.1
Name: llm_atc
Version: 0.1.7
Summary: Tools for fine tuning and serving LLMs
Author: Andrew Aikawa
Author-email: asai@berkeley.edu
Requires-Python: ==3.10.*
Classifier: Programming Language :: Python :: 3
Classifier: Programming Language :: Python :: 3.10
Requires-Dist: click (>=8.1.6,<9.0.0)
Requires-Dist: omegaconf (>=2.3.0,<3.0.0)
Requires-Dist: posthog (>=3.0.1,<4.0.0)
Requires-Dist: prettytable (>=3.8.0,<4.0.0)
Requires-Dist: skypilot (>=0.4.1,<0.5.0)
